telescopius/__init__.py
telescopius/client.py
telescopius/exceptions.py
telescopius/py.typed
telescopius_api-1.0.0.dist-info/METADATA
telescopius_api-1.0.0.dist-info/WHEEL
telescopius_api-1.0.0.dist-info/RECORD
