Metadata-Version: 2.4
Name: telescopius-api
Version: 1.0.0
Summary: Python SDK for the Telescopius REST API - Search astronomical targets and plan observations
Project-URL: Homepage, https://api.telescopius.com
Project-URL: Documentation, https://api.telescopius.com
Project-URL: Repository, https://github.com/telescopius/telescopius-api-python
Author: Carl Svensson
License-Expression: MIT
Keywords: api,astronomy,astrophotography,celestial,deep-sky,observation,planning,telescopius
Classifier: Development Status :: 5 - Production/Stable
Classifier: Intended Audience :: Developers
Classifier: Intended Audience :: Science/Research
Classifier: License :: OSI Approved :: MIT License
Classifier: Operating System :: OS Independent
Classifier: Programming Language :: Python :: 3
Classifier: Programming Language :: Python :: 3.10
Classifier: Programming Language :: Python :: 3.11
Classifier: Programming Language :: Python :: 3.12
Classifier: Programming Language :: Python :: 3.13
Classifier: Topic :: Scientific/Engineering :: Astronomy
Classifier: Typing :: Typed
Requires-Python: >=3.10
Requires-Dist: httpx>=0.25.0
Provides-Extra: dev
Requires-Dist: mypy>=1.0; extra == 'dev'
Requires-Dist: pytest-cov>=4.0; extra == 'dev'
Requires-Dist: pytest-httpx>=0.30.0; extra == 'dev'
Requires-Dist: pytest>=7.0; extra == 'dev'
Requires-Dist: ruff>=0.1.0; extra == 'dev'
